[
  {
    "name": "JADE",
    "path": "facmods/Jade-1.18.2-forge-5.3.0.jar",
    "defaultEnabled": true
  },
  {
    "name": "Just Enough Items",
    "path": "facmods/jei-1.18.2-forge-10.2.1.1005.jar",
    "defaultEnabled": true
  },
  {
    "name": "JourneyMap",
    "path": "facmods/journeymap-1.18.2-5.9.7-forge.jar",
    "defaultEnabled": true
  },
  {
    "name": "Just Zoom",
    "path": "facmods/justzoom_forge_1.0.2-1_MC_1.18.2.jar",
    "defaultEnabled": true
  },
  {
    "name":  "BetterThirdPerson",
    "path": "facmods/BetterThirdPerson-Forge-1.18.2-1.9.0.jar",
    "defaultEnabled": false
  },
  {
    "name": "LegendaryTooltips",
    "path": "facmods/LegendaryTooltips-1.18.2-1.3.1.jar",
    "defaultEnabled": false
  },
  {
    "name": "Prism (Nécessaire pour LegendaryTooltips)",
    "path": "facmods/libs/Prism-1.18.2-1.0.1.jar",
    "defaultEnabled": true
  },
  {
    "name": "Iceberg (Nécessaire pour LegendaryTooltips)",
    "path": "facmods/libs/Iceberg-1.18.2-forge-1.0.49.jar",
    "defaultEnabled": true
  },
  {
    "name": "InventoryProfiles",
    "path": "facmods/Inventory-Profiles-Mod-Forge-1.18.2.jar",
    "defaultEnabled": true
  },
  {
    "name": "KFF (nécessaire pour InventoryProfiles)",
    "path": "facmods/kotlinforforge-3.4.0-obf.jar",
    "defaultEnabled": true
  },
  {
    "name": "LibIPN (Nécessaire pour LegendaryTooltips)",
    "path": "facmods/libs/libIPN-forge-1.18.2-3.0.2.jar",
    "defaultEnabled":  true
  }
]
